odoo/addons/shopinvader_locomotive_elasticsearch/__init__.py
odoo/addons/shopinvader_locomotive_elasticsearch/__manifest__.py
odoo/addons/shopinvader_locomotive_elasticsearch/component/__init__.py
odoo/addons/shopinvader_locomotive_elasticsearch/component/shopinvader_site_export_mapper.py
odoo/addons/shopinvader_locomotive_elasticsearch/tests/__init__.py
odoo/addons/shopinvader_locomotive_elasticsearch/tests/test_search_engine_site_export.py
odoo12_addon_shopinvader_locomotive_elasticsearch-12.0.1.1.1.dist-info/METADATA
odoo12_addon_shopinvader_locomotive_elasticsearch-12.0.1.1.1.dist-info/WHEEL
odoo12_addon_shopinvader_locomotive_elasticsearch-12.0.1.1.1.dist-info/top_level.txt
odoo12_addon_shopinvader_locomotive_elasticsearch-12.0.1.1.1.dist-info/RECORD
