Metadata-Version: 2.1
Name: odoo12-addon-shopinvader-locomotive-elasticsearch
Version: 12.0.1.1.1
Summary: This addons is used to push the initial elasticsearch configuration to locomotive
Home-page: https://acsone.eu/
Author: ACSONE SA/NV
License: AGPL-3
Platform: UNKNOWN
Classifier: Programming Language :: Python
Classifier: Framework :: Odoo
Classifier: License :: OSI Approved :: GNU Affero General Public License v3
Requires-Python: >=3.5
Requires-Dist: odoo12-addon-component
Requires-Dist: odoo12-addon-shopinvader-elasticsearch
Requires-Dist: odoo12-addon-shopinvader-locomotive
Requires-Dist: odoo (<12.1dev,>=12.0a)
